{
// CGRateS Configuration file
//


"general": {
	"log_level": 7,
	"reply_timeout": "50s",
},


"listen": {
	"rpc_json": ":2012",
	"rpc_gob": ":2013",
	"http": ":2080",
},

"data_db": {								// database used to store runtime data (eg: accounts, cdr stats)
	"db_type": "redis",						// data_db type: <redis|mongo>
	"db_port": 6379, 						// data_db port to reach the database
	"db_name": "10", 						// data_db database name to connect to
},

"stor_db": {
	"db_password": "CGRateS.org",
},


"rals": {
	"enabled": true,
	"thresholds_conns": ["*internal"],
	"max_increments":3000000,
},


"schedulers": {
	"enabled": true,
	"cdrs_conns": ["*internal"],
},


"cdrs": {
	"enabled": true,
	"chargers_conns":["*internal"],
},


"attributes": {
	"enabled": true,
},


"chargers": {
	"enabled": true,
	"attributes_conns": ["*internal"],
},


"resources": {
	"enabled": true,
	"store_interval": "1s",
	"thresholds_conns": ["*internal"]
},


"stats": {
	"enabled": true,
	"store_interval": "1s",
	"thresholds_conns": ["*internal"],
},

"thresholds": {
	"enabled": true,
	"store_interval": "1s",
},


"routes": {
	"enabled": true,
	"prefix_indexed_fields":["*req.Destination"],
	"stats_conns": ["*internal"],
	"resources_conns": ["*internal"],
	"rals_conns": ["*internal"],
},


"sessions": {
	"enabled": true,
	"routes_conns": ["*internal"],
	"resources_conns": ["*internal"],
	"attributes_conns": ["*internal"],
	"rals_conns": ["*internal"],
	"cdrs_conns": ["*internal"],
	"chargers_conns": ["*internal"],
},


"migrator":{
	"out_stordb_password": "CGRateS.org",
	"users_filters":["Account"],
},



"admins": {
	"enabled": true,
	"scheduler_conns": ["*internal"],
},


"filters": {								
	"apiers_conns": ["*internal"],
},

"loader": {											// loader for tariff plans out of .csv files
	"gapi_credentials": {"installed":{"client_id":"569705934960-g3a0st3vt1ukjuar095g8lcj20uoghd4.apps.googleusercontent.com","project_id":"quickstart-1585222428976","auth_uri":"https://accounts.google.com/o/oauth2/auth","token_uri":"https://oauth2.googleapis.com/token","auth_provider_x509_cert_url":"https://www.googleapis.com/oauth2/v1/certs","client_secret":"GEt2tOQs9PEbEUE0jil7Mdi1","redirect_uris":["urn:ietf:wg:oauth:2.0:oob","http://localhost"]}}, 	
	"gapi_token": {"access_token":"ya29.a0Adw1xeWSyini7Tn2SB7hJz6JdWAGfH5cPOOJwt4wipWimI9Bu8yiGhr_aa0aSxyB99bO3_MotqdIuQZtXIZ9zm-POh75RpFbUaw_WagdQGqlI0ku7RCfbMnKWYjbOCCEaIpXaxQrFSc9T0WknnunT-t0wRnwKlNR_yQ","token_type":"Bearer","refresh_token":"1//09RLNyZhMSBPICgYIARAAGAkSNwF-L9Irw03FPhwWY2fjGErCQV33V2KCcAwhw-d9l0Imarlg8x05Xo9sDWL9k3sWm-c0WSYVjFU","expiry":"2020-03-26T14:58:26.741727156+02:00"} 			
},

}
